middl/__init__.py
middl/py.typed
middl/core/__init__.py
middl/core/errors.py
middl/core/loader.py
middl/core/middleware.py
middl/core/pipeline.py
middl-0.0.1a8.dist-info/METADATA
middl-0.0.1a8.dist-info/WHEEL
middl-0.0.1a8.dist-info/licenses/LICENSE
middl-0.0.1a8.dist-info/RECORD
