Metadata-Version: 2.4
Name: middl
Version: 0.0.1a8
Summary: Composable middleware components for creating machine learning pipelines
Author-email: Tadej Svetina <tadej.svetina@gmail.com>
License-File: LICENSE
Requires-Python: >=3.10
